nelson/__init__.py
nelson/abstract.py
nelson/developer.py
nelson/gtomscs.py
nelson/sessionbuilder.py
nelson/udacity.py
nelson/uploadcallbacks.py
nelson/clyde_sample/console.py
nelson/clyde_sample/grade.py
nelson/clyde_sample/run.py
nelson/clyde_sample/workspace/._gitignore
nelson/clyde_sample/workspace/helloworld.c
nelson/clyde_sample/workspace/main.c
nelson-0.4.3.dist-info/DESCRIPTION.rst
nelson-0.4.3.dist-info/METADATA
nelson-0.4.3.dist-info/RECORD
nelson-0.4.3.dist-info/WHEEL
nelson-0.4.3.dist-info/entry_points.txt
nelson-0.4.3.dist-info/metadata.json
nelson-0.4.3.dist-info/top_level.txt
