Metadata-Version: 2.0
Name: nelson
Version: 0.4.3
Summary: Handling submission of code to Udacity for automatic feedback
Home-page: http://github.com/udacity/nelson
Author: S. Charles Brubaker
Author-email: cb@udacity.com
License: MIT
Keywords: Udacity Georgia Tech OMS
Platform: UNKNOWN
Requires-Dist: future
Requires-Dist: requests (>=2.2.1)
Requires-Dist: requests-toolbelt (>=0.7.0)
